cerebro/__init__.py
cerebro/__main__.py
cerebro/app.py
cerebro/models.py
cerebro/screens/__init__.py
cerebro/screens/chat_screen.py
cerebro/screens/local_models_screen.py
cerebro/screens/site_models_screen.py
cerebro/services/__init__.py
cerebro/services/chat_service.py
cerebro/services/ollama_service.py
cerebro/widgets/__init__.py
cerebro/widgets/chat_panel.py
cerebro/widgets/model_list.py
cerebro/widgets/session_config.py
cerebro/widgets/session_picker.py
cerebro-0.1.0.dist-info/METADATA
cerebro-0.1.0.dist-info/WHEEL
cerebro-0.1.0.dist-info/entry_points.txt
cerebro-0.1.0.dist-info/RECORD
