Metadata-Version: 2.4
Name: CereBro
Version: 0.1.0
Summary: A streamlined TUI for Ollama LLMs
Project-URL: Homepage, https://github.com/therrshan/cerebro
Project-URL: Repository, https://github.com/therrshan/cerebro
Project-URL: Issues, https://github.com/therrshan/cerebro/issues
Author-email: Darshan <therrshan@gmail.com>
License: MIT
Keywords: ai,chat,llm,ollama,tui
Classifier: Development Status :: 4 - Beta
Classifier: Intended Audience :: Developers
Classifier: License :: OSI Approved :: MIT License
Classifier: Programming Language :: Python :: 3
Classifier: Programming Language :: Python :: 3.11
Classifier: Programming Language :: Python :: 3.12
Requires-Python: >=3.11
Requires-Dist: httpx>=0.25.0
Requires-Dist: pydantic>=2.5.0
Requires-Dist: rich>=13.7.0
Requires-Dist: textual>=0.47.0
